check_depz/check_dependencies.py
check_depz-0.18.0.dist-info/METADATA
check_depz-0.18.0.dist-info/WHEEL
check_depz-0.18.0.dist-info/entry_points.txt
check_depz-0.18.0.dist-info/RECORD
