Metadata-Version: 2.3
Name: check-depz
Version: 0.18.0
Summary: 
Author: Henryk Konsek
Author-email: hekonsek@gmail.com
Requires-Python: >=3.12
Classifier: Programming Language :: Python :: 3
Classifier: Programming Language :: Python :: 3.12
Classifier: Programming Language :: Python :: 3.13
Requires-Dist: typer (>=0.16.1)
